websauna.utils-1.0a8-py3.6-nspkg.pth
websauna/utils/__init__.py
websauna/utils/autoevent.py
websauna/utils/crypt.py
websauna/utils/html.py
websauna/utils/jsonb.py
websauna/utils/orderedset.py
websauna/utils/qualname.py
websauna/utils/secrets.py
websauna/utils/slug.py
websauna/utils/time.py
websauna/utils/traverseattribute.py
websauna/utils/compat/__init__.py
websauna/utils/compat/typing.py
websauna/utils/conf/test-secrets.ini
websauna/utils/config/__init__.py
websauna/utils/config/exceptions.py
websauna/utils/config/includer.py
websauna/utils/config/loader.py
websauna/utils/tests/test_utils_crypt.py
websauna/utils/tests/test_utils_html.py
websauna/utils/tests/test_utils_jsonb.py
websauna/utils/tests/test_utils_qualname.py
websauna/utils/tests/test_utils_secrets.py
websauna/utils/tests/test_utils_slug.py
websauna/utils/tests/test_utils_time.py
websauna/utils/tests/test_utils_traverseattribute.py
websauna.utils-1.0a8.dist-info/DESCRIPTION.rst
websauna.utils-1.0a8.dist-info/METADATA
websauna.utils-1.0a8.dist-info/RECORD
websauna.utils-1.0a8.dist-info/WHEEL
websauna.utils-1.0a8.dist-info/entry_points.txt
websauna.utils-1.0a8.dist-info/metadata.json
websauna.utils-1.0a8.dist-info/namespace_packages.txt
websauna.utils-1.0a8.dist-info/top_level.txt
